koda_ac/__init__.py
koda_ac/__main__.py
koda_ac/core.py
koda_ac-0.1.4.dist-info/entry_points.txt
koda_ac-0.1.4.dist-info/WHEEL
koda_ac-0.1.4.dist-info/METADATA
koda_ac-0.1.4.dist-info/RECORD
