Metadata-Version: 2.1
Name: koda-ac
Version: 0.1.4
Summary: 
Home-page: https://github.com/mRokita/KODA
Author: Michał Rokita
Author-email: mrokita@mrokita.pl
Requires-Python: >=3.9,<4.0
Classifier: Programming Language :: Python :: 3
Classifier: Programming Language :: Python :: 3.10
Classifier: Programming Language :: Python :: 3.9
Requires-Dist: matplotlib (>=3.5.2,<4.0.0)
Requires-Dist: rich (>=12.4.4,<13.0.0)
Requires-Dist: typer (>=0.4.1,<0.5.0)
Project-URL: Repository, https://github.com/mRokita/KODA
